{
  "project_info": {
    "project_number": "1028791528109",
    "project_id": "djvmf-ce8e6",
    "storage_bucket": "djvmf-ce8e6.firebasestorage.app"
  },
  "client": [
    {
      "client_info": {
        "mobilesdk_app_id": "1:1028791528109:android:730049b6a4204cacbef424",
        "android_client_info": {
          "package_name": "com.android.application"
        }
      },
      "oauth_client": [],
      "api_key": [
        {
          "current_key": "AIzaSyAN_11GJSyyw9ollalFv91DT62_sTZ35SQ"
        }
      ],
      "services": {
        "appinvite_service": {
          "other_platform_oauth_client": []
        }
      }
    },
    {
      "client_info": {
        "mobilesdk_app_id": "1:1028791528109:android:8bf3f45be42b4b6dbef424",
        "android_client_info": {
          "package_name": "com.example.accessory_app"
        }
      },
      "oauth_client": [],
      "api_key": [
        {
          "current_key": "AIzaSyAN_11GJSyyw9ollalFv91DT62_sTZ35SQ"
        }
      ],
      "services": {
        "appinvite_service": {
          "other_platform_oauth_client": []
        }
      }
    },
    {
      "client_info": {
        "mobilesdk_app_id": "1:1028791528109:android:36c07d9f03b2e0fabef424",
        "android_client_info": {
          "package_name": "kr.co.catalog"
        }
      },
      "oauth_client": [],
      "api_key": [
        {
          "current_key": "AIzaSyAN_11GJSyyw9ollalFv91DT62_sTZ35SQ"
        }
      ],
      "services": {
        "appinvite_service": {
          "other_platform_oauth_client": []
        }
      }
    }
  ],
  "configuration_version": "1"
}